{"b":18,"c":47,"v":[[1,{"ESV":"Clap your hands, all peoples! Shout to God with loud songs of joy!","GAE":"너희 만민들아 손바닥을 치고 즐거운 소리로 하나님께 외칠지어다","NIV":"Clap your hands, all you nations; shout to God with cries of joy.","SAENEW":"만백성아, 손뼉을 쳐라. 하나님께 기쁨의 함성을 외쳐라.","WLB":"오 너희 모든 백성들아, 손뼉을 치라. 승리의 소리로 하나님께 외치라."}],[2,{"ESV":"For the Lord , the Most High, is to be feared, a great king over all the earth.","GAE":"지존하신 여호와는 두려우시고 온 땅에 큰 왕이 되심이로다","NIV":"For the Lord Most High is awesome, the great King over all the earth.","SAENEW":"주님은 두려워할 지존자이시며, 온 땅을 다스리는 크고도 큰 왕이시다.","WLB":"지극히 높으신 여호와는 두려운 분이시다. 온 땅을 다스리시는 위대한 왕이시다."}],[3,{"ESV":"He subdued peoples under us, and nations under our feet.","GAE":"여호와께서 만민을 우리에게, 나라들을 우리 발 아래에 복종하게 하시며","NIV":"He subdued nations under us, peoples under our feet.","SAENEW":"주님은 만백성을 우리에게 복종케 하시고, 뭇 나라를 우리 발 아래 무릎 꿇게 하신다.","WLB":"그분은 사람들을 우리 아래 복종시키시고 저 민족들을 우리 발 아래 두실 것이다."}],[4,{"ESV":"He chose our heritage for us, the pride of Jacob whom he loves. Selah","GAE":"우리를 위하여 기업을 택하시나니 곧 사랑하신 야곱의 영화로다 (셀라)","NIV":"He chose our inheritance for us, the pride of Jacob, whom he loved.","SAENEW":"주님은 우리에게 땅을 선택해 주셨다. 이 땅은 주님께서 사랑하시는 야곱의 자랑거리였다. (셀라)","WLB":"우리를 위해 유산을 선택하셨는데 그것은 바로 그분이 사랑하시는 야곱의 자랑거리다. (셀라)"}],[5,{"ESV":"God has gone up with a shout, the Lord with the sound of a trumpet.","GAE":"하나님께서 즐거운 함성 중에 올라가심이여 여호와께서 나팔 소리 중에 올라가시도다","NIV":"God has ascended amid shouts of joy, the Lord amid the sounding of trumpets.","SAENEW":"환호 소리 크게 울려 퍼진다. 하나님이 보좌에 오르신다. 나팔 소리 크게 울려 퍼진다. 주님이 보좌에 오르신다.","WLB":"기뻐 외치는 소리와 함께 하나님께서 나팔 소리 울리는 가운데 올라가셨다."}],[6,{"ESV":"Sing praises to God, sing praises! Sing praises to our King, sing praises!","GAE":"찬송하라 하나님을 찬송하라 찬송하라 우리 왕을 찬송하라","NIV":"Sing praises to God, sing praises; sing praises to our King, sing praises.","SAENEW":"시로 하나님을 찬양하여라. 시로 찬양하여라. 시로 우리의 왕을 찬양하여라. 시로 찬양하여라.","WLB":"찬양하라. 하나님을 찬양하라. 찬양하라. 우리 왕을 찬양하라."}],[7,{"ESV":"For God is the King of all the earth; sing praises with a psalm!","GAE":"하나님은 온 땅의 왕이심이라 지혜의 시로 찬송할지어다","NIV":"For God is the King of all the earth; sing to him a psalm of praise.","SAENEW":"하나님은 온 땅의 왕이시니, 정성을 다하여 찬양하여라.","WLB":"하나님은 온 땅의 왕이시니 찬양의 시로 노래하라."}],[8,{"ESV":"God reigns over the nations; God sits on his holy throne.","GAE":"하나님이 뭇 백성을 다스리시며 하나님이 그의 거룩한 보좌에 앉으셨도다","NIV":"God reigns over the nations; God is seated on his holy throne.","SAENEW":"하나님은 뭇 나라를 다스리는 왕이시다. 하나님이 그의 거룩한 보좌에 앉으셨다.","WLB":"하나님께서 이방 민족들을 통치하신다. 하나님께서 그 거룩한 옥좌에 앉으셨다."}],[9,{"ESV":"The princes of the peoples gather as the people of the God of Abraham. For the shields of the earth belong to God; he is highly exalted!","GAE":"뭇 나라의 고관들이 모임이여 아브라함의 하나님의 백성이 되도다 세상의 모든 방패는 하나님의 것임이여 그는 높임을 받으시리로다","NIV":"The nobles of the nations assemble as the people of the God of Abraham, for the kings of the earth belong to God; he is greatly exalted.","SAENEW":"온 백성의 통치자들이 아브라함의 하나님의 백성이 되어 다 함께 모였다. 열강의 군왕들은 모두 주님께 속하였다. 하나님은 지존하시다.","WLB":"백성들 가운데 귀족들이 아브라함의 하나님의 백성이 돼 모여 있구나. 이 땅의 방패들이 하나님께 속해 있으니 그분은 지극히 높임을 받으셨도다."}]]}